setup.py
ctw/__init__.py
ctw.egg-info/PKG-INFO
ctw.egg-info/SOURCES.txt
ctw.egg-info/dependency_links.txt
ctw.egg-info/entry_points.txt
ctw.egg-info/requires.txt
ctw.egg-info/top_level.txt