Metadata-Version: 1.0
Name: ctw
Version: 0.0.2
Summary: A script for count solidity codes.
Home-page: https://baidu.com
Author: th35tr0n9
Author-email: th35tr0n9@gmail.com
License: UNKNOWN
Platform: UNKNOWN
